LICENSE
README.md
setup.cfg
setup.py
AaioAsync/__init__.py
AaioAsync/api.py
AaioAsync/requests.py
AaioAsync.egg-info/PKG-INFO
AaioAsync.egg-info/SOURCES.txt
AaioAsync.egg-info/dependency_links.txt
AaioAsync.egg-info/not-zip-safe
AaioAsync.egg-info/requires.txt
AaioAsync.egg-info/top_level.txt
AaioAsync/exceptions/__init__.py
AaioAsync/exceptions/errors.py
AaioAsync/models/balance.py
AaioAsync/models/order.py
AaioAsync/models/withdrawal.py