Metadata-Version: 2.1
Name: AaioAsync
Version: 0.1.10
Summary: Fully async python wrapper for Aaio.io API
Home-page: https://github.com/Belyashik2K/AaioAsync
Author: Belyashik2K
Author-email: lovelybelyashik@gmail.com
License: Apache License, Version 2.0
License-File: LICENSE
